miqc_py/__init__.py
miqc_py/miqc.py
miqc_py-0.0.1.dist-info/METADATA
miqc_py-0.0.1.dist-info/WHEEL
miqc_py-0.0.1.dist-info/top_level.txt
miqc_py-0.0.1.dist-info/RECORD
