Metadata-Version: 2.1
Name: miqc_py
Version: 0.0.1
Summary: Python implementation of miQC method
Author-email: Mark Keller <mark_keller@hms.harvard.edu>
Project-URL: repository, https://github.com/keller-mark/miqc-py
Keywords: single-cell,quality-control,scverse
Classifier: Development Status :: 4 - Beta
Classifier: Intended Audience :: Science/Research
Classifier: Programming Language :: Python :: 3.8
Classifier: Programming Language :: Python :: 3.9
Classifier: Programming Language :: Python :: 3.10
Classifier: Programming Language :: Python :: 3.11
Classifier: Programming Language :: Python :: 3.12
Requires-Python: >=3.7
Requires-Dist: pandas
Requires-Dist: numpy
Requires-Dist: anndata <0.11,>=0.7.8
Requires-Dist: scanpy >=1.9.3
Requires-Dist: stepmix ==2.2.1
Provides-Extra: dev
Requires-Dist: build ==0.1.0 ; extra == 'dev'
Requires-Dist: pytest >=6.2.4 ; extra == 'dev'
Requires-Dist: flake8 ==3.8.4 ; extra == 'dev'
